dsnd_prob_y/Binomialdistribution.py
dsnd_prob_y/Gaussiandistribution.py
dsnd_prob_y/Generaldistribution.py
dsnd_prob_y/__init__.py
dsnd_prob_y-0.1.dist-info/METADATA
dsnd_prob_y-0.1.dist-info/WHEEL
dsnd_prob_y-0.1.dist-info/top_level.txt
dsnd_prob_y-0.1.dist-info/RECORD
