Metadata-Version: 2.1
Name: dsnd-prob-y
Version: 0.1
Summary: Gaussian and Binomial distributions
Home-page: UNKNOWN
Author: Yufei GE
Author-email: UNKNOWN
License: UNKNOWN
Platform: UNKNOWN
